ksfaceapi/__init__.py
ksfaceapi/core.py
ksfaceapi-1.1.1.dist-info/METADATA
ksfaceapi-1.1.1.dist-info/WHEEL
ksfaceapi-1.1.1.dist-info/top_level.txt
ksfaceapi-1.1.1.dist-info/RECORD
