Metadata-Version: 2.1
Name: ksfaceapi
Version: 1.1.1
Summary: A simple Python SDK for Face++ face recognition API
Author: ksfaceapi Team
Author-email: your-email@example.com
Keywords: face recognition,face++,api
Classifier: Development Status :: 4 - Beta
Classifier: Intended Audience :: Developers
Classifier: License :: OSI Approved :: MIT License
Classifier: Operating System :: OS Independent
Classifier: Programming Language :: Python :: 3
Requires-Python: >=3.6
Requires-Dist: requests (>=2.25.0)
Requires-Dist: opencv-python (>=4.5.0)
Requires-Dist: numpy (>=1.19.0)
